titiler/mosaic/__init__.py
titiler/mosaic/errors.py
titiler/mosaic/factory.py
titiler/mosaic/py.typed
titiler/mosaic/extensions/__init__.py
titiler/mosaic/extensions/mosaicjson.py
titiler/mosaic/extensions/wmts.py
titiler/mosaic/extensions/templates/wmts.xml
titiler/mosaic/models/__init__.py
titiler/mosaic/models/responses.py
titiler_mosaic-1.0.2.dist-info/METADATA
titiler_mosaic-1.0.2.dist-info/WHEEL
titiler_mosaic-1.0.2.dist-info/licenses/LICENSE
titiler_mosaic-1.0.2.dist-info/RECORD
